{
  "server": "ia902505.us.archive.org",
  "dir": "/20/items/bgs_demo",
  "metadata": {
	"identifier": [
	  "bgs_demo"
	],
	"mediatype": [
	  "software"
	],
	"collection": [
	  "classicpcgames"
	],
	"creator": [
	  "TalonSoft"
	],
	"date": [
	  "1996"
	],
	"description": [
	  "<div>TalonSoft returns to the age of the American Civil War! A spectacularly rendered battlefield highlights this momentous and bloody struggle, which some have called the beginning of the end for the Confederate States of America.\u00a0<\/div><div><br \/><\/div><div>Battleground Shiloh covers the two days of April 6th and 7th, 1862, when the Confederate Army under Albert Sidney Johnston launched a bold surprise attack on U.S. Grant's Union Army. Lavish attention to detail, gorgeous graphics and full-color re-enactment videos blend into an exciting extravaganza of true multimedia entertainment!\u00a0<\/div>"
	],
	"publisher": [
	  "TalonSoft"
	],
	"scanner": [
	  "Internet Archive HTML5 Uploader 1.5.2"
	],
	"subject": [
	  "Windows games; Vintage computer games; Strategy games"
	],
	"title": [
	  "Battleground 4: Shiloh Demo"
	],
	"year": [
	  "1996"
	],
	"publicdate": [
	  "2014-06-12 02:41:28"
	],
	"addeddate": [
	  "2014-06-12 02:41:28"
	],
	"backup_location": [
	  "ia905809_0"
	]
  },
  "files": {
	"\/bgs_demo.jpg": {
	  "source": "original",
	  "format": "JPEG",
	  "mtime": "1402540887",
	  "size": "456977",
	  "md5": "23c4e8c6ccda866ebb0eee24eb447fe0",
	  "crc32": "f15e6042",
	  "sha1": "856ee7adeb63176321413d9ebbf0838de65229d7",
	  "rotation": "0"
	},
	"\/bgs_demo.rar": {
	  "source": "original",
	  "format": "RAR",
	  "mtime": "1402540932",
	  "size": "25726118",
	  "md5": "b9e30fc80c5a22dbcf4d49ae207d0270",
	  "crc32": "08291467",
	  "sha1": "25056fbcd30b0ef51d8f99d30418ff040b7b46e3"
	},
	"\/bgs_demo_archive.torrent": {
	  "source": "original",
	  "btih": "0183edb40c38cd09cb3c292b32ab31150d721e81",
	  "mtime": "1476126479",
	  "size": "2931",
	  "md5": "e678b79cef2492b76a9e6a5cf6fdf5e6",
	  "crc32": "942d5c28",
	  "sha1": "bfad991db12b3e843b01598422d58ba146b8dd43",
	  "format": "Archive BitTorrent"
	},
	"\/bgs_demo_files.xml": {
	  "source": "original",
	  "format": "Metadata",
	  "md5": "342ebad51b0ee4b29e5e1f4eb80a7881"
	},
	"\/bgs_demo_meta.sqlite": {
	  "source": "original",
	  "format": "Metadata",
	  "mtime": "1402540935",
	  "size": "14336",
	  "md5": "9434401813833269399dc3573953a9a0",
	  "crc32": "03d52b2e",
	  "sha1": "ae3e335f32b0c6d73760dc0e4b68c25d9cab0a5c"
	},
	"\/bgs_demo_meta.xml": {
	  "source": "original",
	  "format": "Metadata",
	  "mtime": "1476126478",
	  "size": "1313",
	  "md5": "6433357c6140eb589d2689ef9fa66a63",
	  "crc32": "8d40c60a",
	  "sha1": "4046f9ee6f8ee637eca2e1b30b12edbea614541d"
	},
	"\/bgs_demo_thumb.jpg": {
	  "source": "derivative",
	  "format": "JPEG Thumb",
	  "original": "bgs_demo.jpg",
	  "mtime": "1402540942",
	  "size": "6935",
	  "md5": "bd7518dfbf54eb86bd1b488f745bad05",
	  "crc32": "1e6dc854",
	  "sha1": "05e126409126606d30f58a507d56c69965d7baec"
	}
  },
  "misc": {
	"image": "https:\/\/ia902505.us.archive.org\/20\/items\/bgs_demo\/bgs_demo_thumb.jpg",
	"collection-title": "Classic PC Games"
  },
  "item": {
	"downloads": 662,
	"week": 16,
	"month": 47
  }
}