{
  "server": "ia902501.us.archive.org",
  "dir": "/15/items/ContraptionsDemo",
  "metadata": {
	"identifier": [
	  "ContraptionsDemo"
	],
	"mediatype": [
	  "software"
	],
	"collection": [
	  "classicpcgames"
	],
	"creator": [
	  "Dynamix"
	],
	"date": [
	  "2001"
	],
	"description": [
	  "<div>Thank you for giving \"The Incredible Machine: Even More Contraptions\" a try! This demo was designed to give you a taste of what the final game has to offer.<\/div><div><br \/><\/div><div>Here are the features of this demo:<\/div><div><br \/><\/div><div>\u00b7 11 Contraptions from \"super-simple\" to \"hair-tearing\"!<\/div><div>\u00b7 3 Two Player contraptions for head to head madness!<\/div><div>\u00b7 33 Parts to build your own madcap contraptions!<\/div>"
	],
	"publisher": [
	  "Sierra On-Line"
	],
	"scanner": [
	  "Internet Archive HTML5 Uploader 1.5.2"
	],
	"subject": [
	  "Windows games; Vintage computer games; Puzzle games"
	],
	"title": [
	  "The Incredible Machine: Even More Contraptions Demo"
	],
	"year": [
	  "2001"
	],
	"publicdate": [
	  "2014-06-02 19:29:41"
	],
	"addeddate": [
	  "2014-06-02 19:29:41"
	],
	"backup_location": [
	  "ia905808_19"
	]
  },
  "files": {
	"\/ContraptionsDemo.jpg": {
	  "source": "original",
	  "format": "JPEG",
	  "mtime": "1401737392",
	  "size": "179920",
	  "md5": "4d5079e9a94b724ba4777763c1b8ad97",
	  "crc32": "1fe521ad",
	  "sha1": "e9d00ac539eefdaef7b4392aec0a87d2db04a773",
	  "rotation": "0"
	},
	"\/ContraptionsDemo.rar": {
	  "source": "original",
	  "format": "RAR",
	  "mtime": "1401737380",
	  "size": "19212528",
	  "md5": "1fa213528396b582d6dec77e9678f74a",
	  "crc32": "489db710",
	  "sha1": "0db8eff716ad5d4aea566cba3cc47702cf0b9f96"
	},
	"\/ContraptionsDemo_archive.torrent": {
	  "source": "original",
	  "btih": "b5415335e6f8c6d232a020bf27b3431d43150c41",
	  "mtime": "1474213033",
	  "size": "2788",
	  "md5": "5507d96f266f555f8a5b5a9e71b47e0c",
	  "crc32": "78a0764b",
	  "sha1": "745c248983fe57e73ee5a475da498144bc4c039e",
	  "format": "Archive BitTorrent"
	},
	"\/ContraptionsDemo_files.xml": {
	  "source": "original",
	  "format": "Metadata",
	  "md5": "23b376c59b9c21f1479734609026db4d"
	},
	"\/ContraptionsDemo_meta.sqlite": {
	  "source": "original",
	  "format": "Metadata",
	  "mtime": "1401737400",
	  "size": "15360",
	  "md5": "65e469602b36b168e4267899582a4b8a",
	  "crc32": "9328519a",
	  "sha1": "eed7f35e9e85f112e60d235f2339869521ac276a"
	},
	"\/ContraptionsDemo_meta.xml": {
	  "source": "original",
	  "format": "Metadata",
	  "mtime": "1474213033",
	  "size": "1240",
	  "md5": "6b1274dfcece80cafe9a0db9dcbcf173",
	  "crc32": "77ddc969",
	  "sha1": "65ea08a58fb54b6abb9864cee455c30901a9bced"
	},
	"\/ContraptionsDemo_thumb.jpg": {
	  "source": "derivative",
	  "format": "JPEG Thumb",
	  "original": "ContraptionsDemo.jpg",
	  "mtime": "1401737409",
	  "size": "4542",
	  "md5": "9801c006221fffdba05c7643570a7617",
	  "crc32": "2572dcc7",
	  "sha1": "fcab0e23cf57a360281e56382c0b8c003ace6187"
	}
  },
  "misc": {
	"image": "https:\/\/ia902501.us.archive.org\/15\/items\/ContraptionsDemo\/ContraptionsDemo_thumb.jpg",
	"collection-title": "Classic PC Games"
  },
  "item": {
	"downloads": 1676,
	"week": 20,
	"month": 65
  }
}