{
  "server": "ia902509.us.archive.org",
  "dir": "/29/items/CRUSH_201406",
  "metadata": {
	"identifier": [
	  "CRUSH_201406"
	],
	"mediatype": [
	  "software"
	],
	"collection": [
	  "classicpcgames"
	],
	"creator": [
	  "Stone Jackal Studios"
	],
	"date": [
	  "1997"
	],
	"description": [
	  "CRUSH! is a exciting turned based strategy sports game of mayhem and carnage set far into the future. Aliens and men battle through labyrinth like arenas in a frantic search for the B.A.L.L. (Bionic, Augmented, Lower, Life form). The first team to find the ball and reach the goal wins! If your idea of fun is bone crunching checks and raging battles for possession then look no further. CRUSH! the season is open!"
	],
	"publisher": [
	  "Megamedia"
	],
	"scanner": [
	  "Internet Archive HTML5 Uploader 1.5.2"
	],
	"subject": [
	  "Windows games; Vintage computer games; Strategy games"
	],
	"title": [
	  "Crush! Deluxe Demo"
	],
	"year": [
	  "1997"
	],
	"publicdate": [
	  "2014-06-30 22:47:01"
	],
	"addeddate": [
	  "2014-06-30 22:47:01"
	],
	"backup_location": [
	  "ia905809_29"
	]
  },
  "files": {
	"\/CRUSH.rar": {
	  "source": "original",
	  "format": "RAR",
	  "mtime": "1404168447",
	  "size": "6573872",
	  "md5": "82f075b650b1ab18f69f9ceb853478cd",
	  "crc32": "b78af7ea",
	  "sha1": "f36bb1029c746f21d7716719900e9e147a9687b2"
	},
	"\/CRUSH_201406_archive.torrent": {
	  "source": "original",
	  "btih": "cc4ea40f9cf3e7b1709c39e83fff416a12703715",
	  "mtime": "1474297200",
	  "size": "2215",
	  "md5": "3367cdf0409fd8a03bff9f39f011669c",
	  "crc32": "529d223e",
	  "sha1": "551273bcb715a898dcee8a44cf1b816dc5740572",
	  "format": "Archive BitTorrent"
	},
	"\/CRUSH_201406_files.xml": {
	  "source": "original",
	  "format": "Metadata",
	  "md5": "dc03793342e9cae24cc83aa778f3ea32"
	},
	"\/CRUSH_201406_meta.sqlite": {
	  "source": "original",
	  "format": "Metadata",
	  "mtime": "1404168451",
	  "size": "14336",
	  "md5": "da827b29403106100cbf2ce7dd153952",
	  "crc32": "f2e43bbe",
	  "sha1": "b88a804bb3ef5981959670ac693fc0d126d39d11"
	},
	"\/CRUSH_201406_meta.xml": {
	  "source": "original",
	  "format": "Metadata",
	  "mtime": "1474297200",
	  "size": "1090",
	  "md5": "6306a02ffc95b2e24a21b2a63d3b1aa2",
	  "crc32": "233bea77",
	  "sha1": "c936b7f2a2b5ec45ef09458239851d5efc6a8a3d"
	},
	"\/crush.png": {
	  "source": "original",
	  "format": "PNG",
	  "mtime": "1404168421",
	  "size": "76885",
	  "md5": "c62a1019ddaeaab32f7cf3396ea163b5",
	  "crc32": "1b7ef84b",
	  "sha1": "ebf8aa6572ad560159b9c19b119727a203d9edd7"
	},
	"\/crush_thumb.jpg": {
	  "source": "derivative",
	  "format": "JPEG Thumb",
	  "original": "crush.png",
	  "mtime": "1404168456",
	  "size": "5915",
	  "md5": "dfc9b655260947fba0cfc65ca7cbc5ce",
	  "crc32": "d483f801",
	  "sha1": "dc1944dfe8a1f796b10cd894e7dc08c215cccf2f"
	}
  },
  "misc": {
	"image": "https:\/\/ia902509.us.archive.org\/29\/items\/CRUSH_201406\/crush_thumb.jpg",
	"collection-title": "Classic PC Games"
  },
  "item": {
	"downloads": 78,
	"week": 4,
	"month": 4
  }
}