{
  "server": "ia601805.us.archive.org",
  "dir": "/13/items/SpaceEmpires4Gold",
  "metadata": {
	"identifier": [
	  "SpaceEmpires4Gold"
	],
	"mediatype": [
	  "software"
	],
	"collection": [
	  "classicpcgames"
	],
	"creator": [
	  "Malfador Machinations"
	],
	"date": [
	  "2002"
	],
	"description": [
	  "<div>Space Empires IV Gold, allows you to take up a challenge in an epic intergalactic 4X strategy game that will keep you glued to your seat for hours.With gameplay options as vast as space itself players will find themselves immersed in a rich, rewarding gameplay experience unmatched by others in the genre. Gamers are given the power to rule their empire as they see fit. With the wealth of options wannabe galactic emperors won't be left wanting, yet thanks to the hefty manual and intuitive interface, running your empire won't be a headache.<\/div>"
	],
	"publisher": [
	  "Shrapnel Games"
	],
	"scanner": [
	  "Internet Archive HTML5 Uploader 1.5.2"
	],
	"subject": [
	  "Windows games; Vintage computer games; Strategy games"
	],
	"title": [
	  "Space Empires IV Gold Demo"
	],
	"year": [
	  "2002"
	],
	"publicdate": [
	  "2014-04-16 03:37:28"
	],
	"addeddate": [
	  "2014-04-16 03:37:28"
	],
	"backup_location": [
	  "ia905806_26"
	]
  },
  "files": {
	"\/Space Empires 4 Gold.exe": {
	  "source": "original",
	  "format": "Windows Executable",
	  "mtime": "1397619448",
	  "size": "29620841",
	  "md5": "e17b22f9737bacb8cb20f0f3ad7e7604",
	  "crc32": "1931c286",
	  "sha1": "8963d8e1e06cc716a85c3a1715a7acfa38b445af"
	},
	"\/Space Empires 4 Gold.png": {
	  "source": "original",
	  "format": "PNG",
	  "mtime": "1397619460",
	  "size": "113786",
	  "md5": "dab7b0b72376a5b0e3b1bde6be01dbcc",
	  "crc32": "54ffa642",
	  "sha1": "932802e9c2bf0cd49fdc5979969aa831f9284394"
	},
	"\/Space Empires 4 Gold_thumb.jpg": {
	  "source": "derivative",
	  "format": "JPEG Thumb",
	  "original": "Space Empires 4 Gold.png",
	  "mtime": "1397619474",
	  "size": "5565",
	  "md5": "c32f0028c065bcab0ad0a52212076d4f",
	  "crc32": "dfb0ed04",
	  "sha1": "19f8e0cda92f248588e4bcd822bb958cc24a7788"
	},
	"\/SpaceEmpires4Gold_archive.torrent": {
	  "source": "original",
	  "btih": "472744bd513c28981883de7f20e2c03103ea0fc1",
	  "mtime": "1474381300",
	  "size": "3190",
	  "md5": "ba560fa90296b3b8a552d8baa8d1b956",
	  "crc32": "71ff20d3",
	  "sha1": "c0f0a48c0e5ae3867d72e6ff6d79aa748ddb2450",
	  "format": "Archive BitTorrent"
	},
	"\/SpaceEmpires4Gold_files.xml": {
	  "source": "original",
	  "format": "Metadata",
	  "md5": "ae1adb1123bca4c73cbf8105b6b22899"
	},
	"\/SpaceEmpires4Gold_meta.sqlite": {
	  "source": "original",
	  "format": "Metadata",
	  "mtime": "1397619465",
	  "size": "14336",
	  "md5": "ecf4bab3a281b0f6c24efb761a029949",
	  "crc32": "f8a159da",
	  "sha1": "6caee6476af307e9564105016b264de1ef496e8b"
	},
	"\/SpaceEmpires4Gold_meta.xml": {
	  "source": "original",
	  "format": "Metadata",
	  "mtime": "1474381299",
	  "size": "1261",
	  "md5": "a0e71ba09b6f7a82511c374009437a9e",
	  "crc32": "b3145418",
	  "sha1": "8aeaad204ee4f10547a73187531f3e3ace14028a"
	}
  },
  "misc": {
	"image": "https:\/\/ia601805.us.archive.org\/13\/items\/SpaceEmpires4Gold\/Space%20Empires%204%20Gold_thumb.jpg",
	"collection-title": "Classic PC Games"
  },
  "item": {
	"downloads": 163,
	"week": 5,
	"month": 10
  }
}