{
  "server": "ia902508.us.archive.org",
  "dir": "/11/items/SteelSoldiersDemo",
  "metadata": {
	"identifier": [
	  "SteelSoldiersDemo"
	],
	"mediatype": [
	  "software"
	],
	"collection": [
	  "classicpcgames"
	],
	"creator": [
	  "The Bitmap Brothers"
	],
	"date": [
	  "2001"
	],
	"description": [
	  "<div>Steel Soldiers is a highly unique 3D-action\/strategy game in which the player assumes the role of leader of an army of robots. Players must lead their units into battle to gain territories and destroy the opposing forces. The entire game is laced with the humorous and almost cynical personalities of the individual robot units. Through character voices and animated, cartoon cut scenes, gamers are constantly reminded that war is hell, but it can still be funny. The game s real-time strategy elements are focused on action, thereby keeping the players focus on the battles at hand rather than on resource management.T<\/div>"
	],
	"publisher": [
	  "Eon Digital Entertainment"
	],
	"scanner": [
	  "Internet Archive HTML5 Uploader 1.5.2"
	],
	"subject": [
	  "Windows games; Vintage computer games; Strategy games"
	],
	"title": [
	  "Steel Soldiers Demo"
	],
	"year": [
	  "2001"
	],
	"publicdate": [
	  "2014-06-02 19:14:59"
	],
	"addeddate": [
	  "2014-06-02 19:14:59"
	],
	"backup_location": [
	  "ia905808_19"
	]
  },
  "files": {
	"\/SteelSoldiersDemo.jpg": {
	  "source": "original",
	  "format": "JPEG",
	  "mtime": "1401736499",
	  "size": "165993",
	  "md5": "76fdfdce087bea4fe267022f16a5cd93",
	  "crc32": "28be754c",
	  "sha1": "83cf1edd8ab8e5d3d7d11c2f2e4b05c5d2acf46a",
	  "rotation": "0"
	},
	"\/SteelSoldiersDemo.rar": {
	  "source": "original",
	  "format": "RAR",
	  "mtime": "1401736589",
	  "size": "58189756",
	  "md5": "a64241232d540ad03e8420455ea8bce1",
	  "crc32": "b5240065",
	  "sha1": "1333c2c1457cd83e4fa4e749458bcb12de191ee8"
	},
	"\/SteelSoldiersDemo_archive.torrent": {
	  "source": "original",
	  "btih": "337e8be29a17fe745b3c9a59ebd5234ce17f1c89",
	  "mtime": "1474077351",
	  "size": "4281",
	  "md5": "da17ac1acab2e47d58bdf0bfb2ba8290",
	  "crc32": "06ebe85b",
	  "sha1": "45bbdcfb9b266baf49b511fe687f71deed2bf95f",
	  "format": "Archive BitTorrent"
	},
	"\/SteelSoldiersDemo_files.xml": {
	  "source": "original",
	  "format": "Metadata",
	  "md5": "7848dedc82657f22aa9676f023ef4556"
	},
	"\/SteelSoldiersDemo_meta.sqlite": {
	  "source": "original",
	  "format": "Metadata",
	  "mtime": "1401736594",
	  "size": "14336",
	  "md5": "50f91f2c4e322d737930695846b6f07c",
	  "crc32": "35f155be",
	  "sha1": "c4e27cf23932b3e2f5d692d75f198b1c3f34c1b1"
	},
	"\/SteelSoldiersDemo_meta.xml": {
	  "source": "original",
	  "format": "Metadata",
	  "mtime": "1474077350",
	  "size": "1339",
	  "md5": "ffab2b8975604df3cc065acb44eb0b7f",
	  "crc32": "59785780",
	  "sha1": "184d9481e0db3448f277612b4aa4950d569789e2"
	},
	"\/SteelSoldiersDemo_thumb.jpg": {
	  "source": "derivative",
	  "format": "JPEG Thumb",
	  "original": "SteelSoldiersDemo.jpg",
	  "mtime": "1401736604",
	  "size": "3320",
	  "md5": "e7e4a1083b44560c180925a9280bc4f9",
	  "crc32": "3e672ea1",
	  "sha1": "1ab947d3d071fb7dc119d2246902aa398441d336"
	}
  },
  "misc": {
	"image": "https:\/\/ia902508.us.archive.org\/11\/items\/SteelSoldiersDemo\/SteelSoldiersDemo_thumb.jpg",
	"collection-title": "Classic PC Games"
  },
  "item": {
	"downloads": 985,
	"week": 4,
	"month": 22
  }
}