{
  "server": "ia600302.us.archive.org",
  "dir": "/9/items/UltimaUnderworldTheStygianAbyssDemo",
  "metadata": {
	"mediatype": [
	  "software"
	],
	"collection": [
	  "classicpcgames"
	],
	"title": [
	  "Ultima Underworld: The Stygian Abyss Demo"
	],
	"description": [
	  "You are the Avatar, noblest of heroes. In your day, you have beheld many wonders and proved yourself master of many dungeons. But nothing in your experience prepared you for this - the terror-filled passages of Britannia's underworld.\n\nMany years have passed since your last visit to Britannia. Little did you expect that, when you returned, you would be accused of kidnapping Baron Almric's daughter, Arial - and then be thrown into the Great Stygian Abyss, without so much as a chance to prove your innocence. Only by surviving the dangers of the Abyss and finding the villain who abducted Arial can you restore your good name. But dark hints garnered from all corners of the Abyss reveal that this was no simple kidnapping. The fate of Britannia hangs in the balance as you battle the horrors that lurk at the heart of the Great Stygian Abyss.\n\nA True 3-D Environment! Move Smoothly and continuously through the first virtual reality dungeon. The first-person perspective of The Stygian Abyss puts you right in the thick of the action. Look down on objects at your feet, or up to see creatures hovering overhead. Every wall, precipice, object and character in The Stygian Abyss has been painstakingly modeled in 3-D space. You'll feel like you're actually in the dungeon!\n\nUnparalleled Dungeon Excitement! Explore nearly 25 miles of winding passages, gasping chasms and frigid underground rivers. This multi-level dungeon is full of puzzling traps and fearsome monsters. A sophisticated conversation system allows you to talk with dozens of characters who may assist or hinder you in your quest. You'll do more than kill monsters = The Stygian Abyss will challenge your virtues and your wits, as well as your fighting prowess.\n\nThrilling Combat & Magic! Try a quick, relatively weak attack or take the time to put greater power behind your blow. See your weapon lash out and watch your foe stagger and fall. Each magic spell has a dramatic visual effect.\n\nAutomapping! A sophisticated auto-map feature keeps track of your location. You can even write your own comments right on the map so you'll always remember where each important character or landmark is found.\n\nState of the Art Sound & Graphics! A full, orchestral score and lush, 256-color VGA graphics complete ORIGIN's latest multimedia experience. No words, no still images can prepare you for Ultima Underworld: The Stygian Abyss!"
	],
	"subject": [
	  "DOS games; Vintage computer games; Role playing games"
	],
	"creator": [
	  "Blue Sky Productions"
	],
	"identifier": [
	  "UltimaUnderworldTheStygianAbyssDemo"
	],
	"addeddate": [
	  "2012-07-04 22:24:44"
	],
	"date": [
	  "1992"
	],
	"year": [
	  "1992"
	],
	"publisher": [
	  "ORIGIN Systems"
	],
	"publicdate": [
	  "2012-07-04 22:26:10"
	],
	"curation": [
	  "[curator]jscott@archive.org[\/curator][date]20140308004704[\/date][state]un-dark[\/state][comment]Darked by Mistake[\/comment]"
	],
	"backup_location": [
	  "ia903806_12"
	],
	"emulator_start": [
	  "UWDEMO.EXE"
	],
	"emulator_ext": [
	  "zip"
	],
	"emulator": [
	  "dosbox"
	]
  },
  "files": {
	"\/00_coverscreenshot.jpg": {
	  "source": "original",
	  "mtime": "1475584316",
	  "size": "389267",
	  "md5": "a4a3b330cffd01362a2aac49f00f5217",
	  "crc32": "dc73f491",
	  "sha1": "f91afb785b12f2aa1a332fc94c68e66196b95db2",
	  "format": "JPEG",
	  "rotation": "0"
	},
	"\/00_coverscreenshot_thumb.jpg": {
	  "source": "derivative",
	  "format": "JPEG Thumb",
	  "original": "00_coverscreenshot.jpg",
	  "mtime": "1475584487",
	  "size": "6076",
	  "md5": "563135dafaf3406daecfde4121efec51",
	  "crc32": "dc506444",
	  "sha1": "d789a0756e4690018a3755d14549fcf4eeac7b8b"
	},
	"\/UltimaUnderworldTheStygianAbyssDemo.gif": {
	  "source": "original",
	  "mtime": "1475584452",
	  "size": "110408",
	  "md5": "41c49c2118737c9809fcdc29bbf8a6ac",
	  "crc32": "55f67009",
	  "sha1": "7a63b74967ee27da116c9ac2a7bfdfdb8535cdc8",
	  "format": "Animated GIF"
	},
	"\/UltimaUnderworldTheStygianAbyssDemo_archive.torrent": {
	  "source": "original",
	  "btih": "2396e7b3907297279e400fc472a33598863e603b",
	  "mtime": "1475584570",
	  "size": "20480",
	  "md5": "32fdcd511418daa88f6bbb5f25bf9f1f",
	  "crc32": "525baf35",
	  "sha1": "7b2f4f6e088544f63cb86d5a8aa6476122977cf2",
	  "format": "Archive BitTorrent"
	},
	"\/UltimaUnderworldTheStygianAbyssDemo_files.xml": {
	  "source": "original",
	  "format": "Metadata",
	  "md5": "fff54bb7a953ab4207febb49a6e763e1"
	},
	"\/UltimaUnderworldTheStygianAbyssDemo_meta.sqlite": {
	  "source": "original",
	  "mtime": "1475584480",
	  "size": "36864",
	  "format": "Metadata",
	  "md5": "7cebe923d4457df1c164f7811363f00c",
	  "crc32": "4da7dc22",
	  "sha1": "90db160524581e8704bf68c0652b7bd8c7676b39"
	},
	"\/UltimaUnderworldTheStygianAbyssDemo_meta.xml": {
	  "source": "original",
	  "format": "Metadata",
	  "mtime": "1475584569",
	  "size": "3326",
	  "md5": "12e233d98ff57332f3258369cc08d498",
	  "crc32": "557d16f4",
	  "sha1": "1543b2a498c2ad5267385393432406cbba4f41d3"
	},
	"\/resource_item_114.jpg": {
	  "source": "original",
	  "format": "JPEG",
	  "mtime": "1341440640",
	  "size": "15987",
	  "md5": "42ae15e92b1908467c3107fcda2a83a4",
	  "crc32": "d93741e1",
	  "sha1": "29986a22242ec3f774765530426575da3cfc2e92",
	  "rotation": "0"
	},
	"\/resource_item_114_thumb.jpg": {
	  "source": "derivative",
	  "format": "JPEG Thumb",
	  "original": "resource_item_114.jpg",
	  "mtime": "1341440694",
	  "size": "4523",
	  "md5": "01f7e19167aff05773ed53d97a40350d",
	  "crc32": "26d24a23",
	  "sha1": "668117a70b9abeed3efb9efede86dd50b3fcb3a5"
	},
	"\/screenshot_00.jpg": {
	  "source": "original",
	  "mtime": "1475584319",
	  "size": "389267",
	  "md5": "a4a3b330cffd01362a2aac49f00f5217",
	  "crc32": "dc73f491",
	  "sha1": "f91afb785b12f2aa1a332fc94c68e66196b95db2",
	  "format": "JPEG",
	  "rotation": "0"
	},
	"\/screenshot_00_thumb.jpg": {
	  "source": "derivative",
	  "format": "JPEG Thumb",
	  "original": "screenshot_00.jpg",
	  "mtime": "1475584503",
	  "size": "6076",
	  "md5": "563135dafaf3406daecfde4121efec51",
	  "crc32": "dc506444",
	  "sha1": "d789a0756e4690018a3755d14549fcf4eeac7b8b"
	},
	"\/screenshot_01.jpg": {
	  "source": "original",
	  "mtime": "1475584322",
	  "size": "388359",
	  "md5": "ddf31e2c38c3c71f9058094407e74a99",
	  "crc32": "86fa8e7e",
	  "sha1": "87b7dcdff564908dca02c43e31bb083079ddefe6",
	  "format": "JPEG",
	  "rotation": "0"
	},
	"\/screenshot_01_thumb.jpg": {
	  "source": "derivative",
	  "format": "JPEG Thumb",
	  "original": "screenshot_01.jpg",
	  "mtime": "1475584490",
	  "size": "6058",
	  "md5": "545ae3175ed41be64c18ad6534bbfe1f",
	  "crc32": "f2049a51",
	  "sha1": "e65664fe1b11b843ac31f958087e50a3f6680422"
	},
	"\/screenshot_02.jpg": {
	  "source": "original",
	  "mtime": "1475584324",
	  "size": "388430",
	  "md5": "00df27fe71a2f221763c1ecdae0131b0",
	  "crc32": "0b54099d",
	  "sha1": "b7eaae4780f67c43a375220d863fccfad160957d",
	  "format": "JPEG",
	  "rotation": "0"
	},
	"\/screenshot_02_thumb.jpg": {
	  "source": "derivative",
	  "format": "JPEG Thumb",
	  "original": "screenshot_02.jpg",
	  "mtime": "1475584491",
	  "size": "6054",
	  "md5": "55d2a574790a9238cc46ed45566c320f",
	  "crc32": "368e0ec8",
	  "sha1": "efdf63bd4026cb743b9a51781145a7c866abbc91"
	},
	"\/screenshot_03.jpg": {
	  "source": "original",
	  "mtime": "1475584326",
	  "size": "387534",
	  "md5": "a244a219edca4099d01db2d05e80aab1",
	  "crc32": "953e5b10",
	  "sha1": "a13db30060370f1a0acb6f4f615e3117bebdc923",
	  "format": "JPEG",
	  "rotation": "0"
	},
	"\/screenshot_03_thumb.jpg": {
	  "source": "derivative",
	  "format": "JPEG Thumb",
	  "original": "screenshot_03.jpg",
	  "mtime": "1475584492",
	  "size": "5992",
	  "md5": "13707629c29491022b344ac02f3a0d47",
	  "crc32": "51956562",
	  "sha1": "c3aa8c895f126365f5bc748f227f758e983208eb"
	},
	"\/screenshot_04.jpg": {
	  "source": "original",
	  "mtime": "1475584329",
	  "size": "388451",
	  "md5": "8248ed96e362c0a8f1b1f0b06804849f",
	  "crc32": "bf8be350",
	  "sha1": "16c6713f2fc04de79e24d9bdc01d386b479b59ae",
	  "format": "JPEG",
	  "rotation": "0"
	},
	"\/screenshot_04_thumb.jpg": {
	  "source": "derivative",
	  "format": "JPEG Thumb",
	  "original": "screenshot_04.jpg",
	  "mtime": "1475584494",
	  "size": "6053",
	  "md5": "63280c05bdce1c208a09bfb1b591ac8c",
	  "crc32": "c2602ed4",
	  "sha1": "0c95610bb9ceef3fc06b25b823aeae245e764975"
	},
	"\/screenshot_05.jpg": {
	  "source": "original",
	  "mtime": "1475584331",
	  "size": "235624",
	  "md5": "aecc329169688a73f0178a4d8c8486e1",
	  "crc32": "c8924cd5",
	  "sha1": "9b752497045e2e76dbbc475639a49c5a222ae3b3",
	  "format": "JPEG",
	  "rotation": "0"
	},
	"\/screenshot_05_thumb.jpg": {
	  "source": "derivative",
	  "format": "JPEG Thumb",
	  "original": "screenshot_05.jpg",
	  "mtime": "1475584495",
	  "size": "2486",
	  "md5": "75df851f12ad25041c518f5ee129c76e",
	  "crc32": "2e44c3fb",
	  "sha1": "8688538d1f07bb7335a480bcd975668fed4132aa"
	},
	"\/screenshot_06.jpg": {
	  "source": "original",
	  "mtime": "1475584337",
	  "size": "3284",
	  "md5": "c7fe21900a9891233cea1751d2555d34",
	  "crc32": "a8da4401",
	  "sha1": "478cf0778eedeab11e46358360dc8373a4ecd079",
	  "format": "JPEG",
	  "rotation": "0"
	},
	"\/screenshot_06_thumb.jpg": {
	  "source": "derivative",
	  "format": "JPEG Thumb",
	  "original": "screenshot_06.jpg",
	  "mtime": "1475584497",
	  "size": "1011",
	  "md5": "c96d922005e073e59fa1fbc3456198fc",
	  "crc32": "6a5a2747",
	  "sha1": "e83a07ebcc9e4ddc40a2422d881805658fb80717"
	},
	"\/screenshot_07.jpg": {
	  "source": "original",
	  "mtime": "1475584340",
	  "size": "274049",
	  "md5": "c63cbf5e37dafe6b56aaff26655fd5a0",
	  "crc32": "0be7cf85",
	  "sha1": "d3540865f075d82649f4c9b752ee60d83f6f26a2",
	  "format": "JPEG",
	  "rotation": "0"
	},
	"\/screenshot_07_thumb.jpg": {
	  "source": "derivative",
	  "format": "JPEG Thumb",
	  "original": "screenshot_07.jpg",
	  "mtime": "1475584498",
	  "size": "4422",
	  "md5": "5d7bbdb6e62116e4e57842cda403c9e0",
	  "crc32": "9438824f",
	  "sha1": "8a6a2c76fbf4c2699bfa83c36217b220ce2c276d"
	},
	"\/screenshot_08.jpg": {
	  "source": "original",
	  "mtime": "1475584342",
	  "size": "274665",
	  "md5": "cecdca686a7fd9914c475e854e998e24",
	  "crc32": "6aeb9afd",
	  "sha1": "7a65646fe78f715ab16fc07c52c19c23c7692a5a",
	  "format": "JPEG",
	  "rotation": "0"
	},
	"\/screenshot_08_thumb.jpg": {
	  "source": "derivative",
	  "format": "JPEG Thumb",
	  "original": "screenshot_08.jpg",
	  "mtime": "1475584499",
	  "size": "4452",
	  "md5": "20dc333e093fb234689ed8d6f04944ce",
	  "crc32": "6006692f",
	  "sha1": "d8ed3d99a15edcfa24c1d42a7a5b0ca65258d955"
	},
	"\/screenshot_09.jpg": {
	  "source": "original",
	  "mtime": "1475584344",
	  "size": "281282",
	  "md5": "94d00123aad02842423806fbe27a8116",
	  "crc32": "68b88949",
	  "sha1": "25bfc5adf134d5c09eb1ee615fee032a84b26bfe",
	  "format": "JPEG",
	  "rotation": "0"
	},
	"\/screenshot_09_thumb.jpg": {
	  "source": "derivative",
	  "format": "JPEG Thumb",
	  "original": "screenshot_09.jpg",
	  "mtime": "1475584500",
	  "size": "4484",
	  "md5": "1845b86cbc32b3c6745e7b27ea891de8",
	  "crc32": "78f99401",
	  "sha1": "8194e80b7afcc4a495963ba2d1d60058302dd607"
	},
	"\/screenshot_10.jpg": {
	  "source": "original",
	  "mtime": "1475584346",
	  "size": "285649",
	  "md5": "f74361eebdd1e3cc9ef98e4638fb2ad4",
	  "crc32": "3ba68c41",
	  "sha1": "0e405d2cdbb7f32d9a7cb01d74959852a04831c8",
	  "format": "JPEG",
	  "rotation": "0"
	},
	"\/screenshot_10_thumb.jpg": {
	  "source": "derivative",
	  "format": "JPEG Thumb",
	  "original": "screenshot_10.jpg",
	  "mtime": "1475584524",
	  "size": "4509",
	  "md5": "0e318a89104b876df2fbd2a8b16a23a6",
	  "crc32": "bfda18da",
	  "sha1": "ac93ea3062b43512ca8b36a44b1778df729529ba"
	},
	"\/screenshot_11.jpg": {
	  "source": "original",
	  "mtime": "1475584349",
	  "size": "285618",
	  "md5": "f3903c4a6c71ec096b4b05949c0fbc43",
	  "crc32": "0e09ea24",
	  "sha1": "dc83cf5739f2c91761cd868dfa27822764cbc42b",
	  "format": "JPEG",
	  "rotation": "0"
	},
	"\/screenshot_11_thumb.jpg": {
	  "source": "derivative",
	  "format": "JPEG Thumb",
	  "original": "screenshot_11.jpg",
	  "mtime": "1475584488",
	  "size": "4509",
	  "md5": "f1170f25f136af6aeb51e1bc31d02f59",
	  "crc32": "c3f71869",
	  "sha1": "6e4ab08ac94f5d1f2f7d84696d821538c1f13f5c"
	},
	"\/screenshot_12.jpg": {
	  "source": "original",
	  "mtime": "1475584351",
	  "size": "283546",
	  "md5": "3c5d2f2b5136eab5cb018538d93291ee",
	  "crc32": "86f0e56d",
	  "sha1": "15fe95a3d8c591ab58ae23f6727cdfd1617fe060",
	  "format": "JPEG",
	  "rotation": "0"
	},
	"\/screenshot_12_thumb.jpg": {
	  "source": "derivative",
	  "format": "JPEG Thumb",
	  "original": "screenshot_12.jpg",
	  "mtime": "1475584504",
	  "size": "4532",
	  "md5": "72629f9f63d5cd327ea6c39fde43b7c3",
	  "crc32": "78296302",
	  "sha1": "022fc6498203159c90daf2d6293bc93de1ddbda6"
	},
	"\/screenshot_13.jpg": {
	  "source": "original",
	  "mtime": "1475584355",
	  "size": "283408",
	  "md5": "10ba846b5b385cd417647a0d190b3025",
	  "crc32": "d2964652",
	  "sha1": "a821ba279f3735fc05371ff28071d19eae52a86f",
	  "format": "JPEG",
	  "rotation": "0"
	},
	"\/screenshot_13_thumb.jpg": {
	  "source": "derivative",
	  "format": "JPEG Thumb",
	  "original": "screenshot_13.jpg",
	  "mtime": "1475584507",
	  "size": "4575",
	  "md5": "aed827c17bbaea417514f2aecabe013a",
	  "crc32": "a51be395",
	  "sha1": "6a213fd46132cd8efa7c790b04d6fac04fa5b724"
	},
	"\/screenshot_14.jpg": {
	  "source": "original",
	  "mtime": "1475584357",
	  "size": "281817",
	  "md5": "5b27f0bc8f8b3c92a3bfb63de3edacc5",
	  "crc32": "98d05a66",
	  "sha1": "7de79fdf88a80829150b357b3d8f3ba2b5301f2b",
	  "format": "JPEG",
	  "rotation": "0"
	},
	"\/screenshot_14_thumb.jpg": {
	  "source": "derivative",
	  "format": "JPEG Thumb",
	  "original": "screenshot_14.jpg",
	  "mtime": "1475584508",
	  "size": "4572",
	  "md5": "21b798bcbf7e027623e75d231c191de4",
	  "crc32": "326fd349",
	  "sha1": "4ae1862a1e28e3f33684a939f44dc3c17c0971cc"
	},
	"\/screenshot_15.jpg": {
	  "source": "original",
	  "mtime": "1475584361",
	  "size": "282335",
	  "md5": "706e7f910e92b62843615fda2211730d",
	  "crc32": "d5ee7570",
	  "sha1": "0ca98937baee43603381669afe84fb9bcd365a9a",
	  "format": "JPEG",
	  "rotation": "0"
	},
	"\/screenshot_15_thumb.jpg": {
	  "source": "derivative",
	  "format": "JPEG Thumb",
	  "original": "screenshot_15.jpg",
	  "mtime": "1475584510",
	  "size": "4597",
	  "md5": "d21687f3e294ea9470317545126273c9",
	  "crc32": "9892aeba",
	  "sha1": "3902db72855de0f1b10a109916b2554fc5a8078c"
	},
	"\/screenshot_16.jpg": {
	  "source": "original",
	  "mtime": "1475584363",
	  "size": "286202",
	  "md5": "937a4c15b334782912ded63bc9cd6e90",
	  "crc32": "dcaffe07",
	  "sha1": "2b96934011f8a2513bd9cc67352a5148001072c2",
	  "format": "JPEG",
	  "rotation": "0"
	},
	"\/screenshot_16_thumb.jpg": {
	  "source": "derivative",
	  "format": "JPEG Thumb",
	  "original": "screenshot_16.jpg",
	  "mtime": "1475584512",
	  "size": "4630",
	  "md5": "52f74d0deee912c3de532668302416c4",
	  "crc32": "87ce040f",
	  "sha1": "393753305767ea0a42fdb144e89efde2ca26ee31"
	},
	"\/screenshot_17.jpg": {
	  "source": "original",
	  "mtime": "1475584369",
	  "size": "286087",
	  "md5": "2e1a6ea214b1ff24bd18b3f8bf121ee2",
	  "crc32": "5462559f",
	  "sha1": "9f5c71f6fb4790b3a335ae7279a27c6bb49a9037",
	  "format": "JPEG",
	  "rotation": "0"
	},
	"\/screenshot_17_thumb.jpg": {
	  "source": "derivative",
	  "format": "JPEG Thumb",
	  "original": "screenshot_17.jpg",
	  "mtime": "1475584514",
	  "size": "4627",
	  "md5": "cc92f9480189f2efe3763f3b87c17156",
	  "crc32": "75bded6f",
	  "sha1": "8eb0400dd2dc3c911546fa33b75b2c8ad35add4d"
	},
	"\/screenshot_18.jpg": {
	  "source": "original",
	  "mtime": "1475584371",
	  "size": "286232",
	  "md5": "dd14c5047d951362346183c3377fa4a5",
	  "crc32": "2d9d86f5",
	  "sha1": "113b667ea7b7aaf1804ece79b03c706006d8dcea",
	  "format": "JPEG",
	  "rotation": "0"
	},
	"\/screenshot_18_thumb.jpg": {
	  "source": "derivative",
	  "format": "JPEG Thumb",
	  "original": "screenshot_18.jpg",
	  "mtime": "1475584518",
	  "size": "4612",
	  "md5": "4ad66660b9b78e7867056ad7bfacb14f",
	  "crc32": "0240ea1b",
	  "sha1": "3c63665a7168ece994ea5e3836cafb5a3d46d583"
	},
	"\/screenshot_19.jpg": {
	  "source": "original",
	  "mtime": "1475584373",
	  "size": "286352",
	  "md5": "16ad50532c18e4aec8641a20f12fb785",
	  "crc32": "3a6e5e53",
	  "sha1": "8d24abcc8a98b52841dedf4600cb567890f5cd5e",
	  "format": "JPEG",
	  "rotation": "0"
	},
	"\/screenshot_19_thumb.jpg": {
	  "source": "derivative",
	  "format": "JPEG Thumb",
	  "original": "screenshot_19.jpg",
	  "mtime": "1475584520",
	  "size": "4616",
	  "md5": "c15adb0fe81c6dd1120a9c196879ce95",
	  "crc32": "6e489eb2",
	  "sha1": "1ac3a912f43b22b55bf4d7046e281429a19fe164"
	},
	"\/screenshot_20.jpg": {
	  "source": "original",
	  "mtime": "1475584376",
	  "size": "286139",
	  "md5": "b76b3afddf13112e44772e1906fb8df3",
	  "crc32": "5c0ed3c5",
	  "sha1": "b813df5d9b17de0a6f9a59c39a2d7e6d64c3e2fa",
	  "format": "JPEG",
	  "rotation": "0"
	},
	"\/screenshot_20_thumb.jpg": {
	  "source": "derivative",
	  "format": "JPEG Thumb",
	  "original": "screenshot_20.jpg",
	  "mtime": "1475584522",
	  "size": "4617",
	  "md5": "154325013f6249de48be6f67ba066b44",
	  "crc32": "11c20b95",
	  "sha1": "8c1c8dc29cd91f9ebd784d6319c08e26a03d5869"
	},
	"\/screenshot_21.jpg": {
	  "source": "original",
	  "mtime": "1475584378",
	  "size": "287666",
	  "md5": "08ed2df8be18dc04d5506640c1d726f4",
	  "crc32": "968a9d3a",
	  "sha1": "4cf2d1935aa044141bfad28813f18577be03baf1",
	  "format": "JPEG",
	  "rotation": "0"
	},
	"\/screenshot_21_thumb.jpg": {
	  "source": "derivative",
	  "format": "JPEG Thumb",
	  "original": "screenshot_21.jpg",
	  "mtime": "1475584523",
	  "size": "4673",
	  "md5": "4cf71ddd173b87855cef9aa16e332310",
	  "crc32": "d4a488e6",
	  "sha1": "d49d42f3741647b9799c978e81b9a95e2e198980"
	},
	"\/screenshot_22.jpg": {
	  "source": "original",
	  "mtime": "1475584381",
	  "size": "287668",
	  "md5": "d4d475fbfd303d0b427057756f4f1abc",
	  "crc32": "45d3516e",
	  "sha1": "f0846008d5c4744ec2808eb6601c26b2d8bb6c5f",
	  "format": "JPEG",
	  "rotation": "0"
	},
	"\/screenshot_22_thumb.jpg": {
	  "source": "derivative",
	  "format": "JPEG Thumb",
	  "original": "screenshot_22.jpg",
	  "mtime": "1475584502",
	  "size": "4673",
	  "md5": "c167805d87d4674b93070b47235e2029",
	  "crc32": "82e69bdf",
	  "sha1": "153ef32d74be4456b032c590ec7a61f5e85724df"
	},
	"\/screenshot_23.jpg": {
	  "source": "original",
	  "mtime": "1475584383",
	  "size": "287667",
	  "md5": "2fc2da77ea34ed9e8384b986e9f2935a",
	  "crc32": "7f26146b",
	  "sha1": "f49f2a402ca8161a21ce2067b74e4af2ff17f942",
	  "format": "JPEG",
	  "rotation": "0"
	},
	"\/screenshot_23_thumb.jpg": {
	  "source": "derivative",
	  "format": "JPEG Thumb",
	  "original": "screenshot_23.jpg",
	  "mtime": "1475584526",
	  "size": "4673",
	  "md5": "338a23ada0a0bc615ecc6a5ecaa1ce9a",
	  "crc32": "72ad5e97",
	  "sha1": "11939d7ef9fb643df7cef4769b49caf0f9cf2c66"
	},
	"\/screenshot_24.jpg": {
	  "source": "original",
	  "mtime": "1475584385",
	  "size": "297116",
	  "md5": "d0fb79c1dd6cb4b579adead850f99cbd",
	  "crc32": "3f04b5f2",
	  "sha1": "eb6ea57952decd298f82c5f8815929da7a095a46",
	  "format": "JPEG",
	  "rotation": "0"
	},
	"\/screenshot_24_thumb.jpg": {
	  "source": "derivative",
	  "format": "JPEG Thumb",
	  "original": "screenshot_24.jpg",
	  "mtime": "1475584543",
	  "size": "4896",
	  "md5": "fe141dc9f8f8399512d1727b22e2d101",
	  "crc32": "b28e6291",
	  "sha1": "0c0281b30dfc9f0d92b3250dd77206efc83669dd"
	},
	"\/screenshot_25.jpg": {
	  "source": "original",
	  "mtime": "1475584388",
	  "size": "297110",
	  "md5": "3d9b82c564ccf82b9c32e216474e7c5c",
	  "crc32": "26788174",
	  "sha1": "72e97683c1a7e4dd340ebc3e57c22748364b6bb9",
	  "format": "JPEG",
	  "rotation": "0"
	},
	"\/screenshot_25_thumb.jpg": {
	  "source": "derivative",
	  "format": "JPEG Thumb",
	  "original": "screenshot_25.jpg",
	  "mtime": "1475584544",
	  "size": "4896",
	  "md5": "39b2c24bc0b55abf2168d5ea0d537bb4",
	  "crc32": "ba2a22c9",
	  "sha1": "31c0b910aa09313082a9b0ba661f4d7a85cb72fd"
	},
	"\/screenshot_26.jpg": {
	  "source": "original",
	  "mtime": "1475584391",
	  "size": "297127",
	  "md5": "896635fa97c2e0dc0400ef15f91adc4e",
	  "crc32": "8027296a",
	  "sha1": "ae7d3faf24fcdd42d67c1ac9744943c6c87928db",
	  "format": "JPEG",
	  "rotation": "0"
	},
	"\/screenshot_26_thumb.jpg": {
	  "source": "derivative",
	  "format": "JPEG Thumb",
	  "original": "screenshot_26.jpg",
	  "mtime": "1475584530",
	  "size": "4890",
	  "md5": "4f4ae2da30248057fa0b6b9a81c753b5",
	  "crc32": "301279a9",
	  "sha1": "814ea2351516b02eb01fcf173981adc30c5b01e8"
	},
	"\/screenshot_27.jpg": {
	  "source": "original",
	  "mtime": "1475584394",
	  "size": "297435",
	  "md5": "96fbf4acdce6c81d14522a6148b9a37e",
	  "crc32": "a99aa620",
	  "sha1": "b50af2586560f922762ebc6f9ac4047cbfbf8783",
	  "format": "JPEG",
	  "rotation": "0"
	},
	"\/screenshot_27_thumb.jpg": {
	  "source": "derivative",
	  "format": "JPEG Thumb",
	  "original": "screenshot_27.jpg",
	  "mtime": "1475584531",
	  "size": "4903",
	  "md5": "f5e91c09c8ff823f59b2ff8506989431",
	  "crc32": "636c105a",
	  "sha1": "96cd2c6e26a28ba119adb94f54b799331985838a"
	},
	"\/screenshot_28.jpg": {
	  "source": "original",
	  "mtime": "1475584396",
	  "size": "296553",
	  "md5": "4d99e5b1ee2d0f1379e8b186540be9ae",
	  "crc32": "ecda448d",
	  "sha1": "d326cdd69f79fe6c9201a2f11d3b42080601c068",
	  "format": "JPEG",
	  "rotation": "0"
	},
	"\/screenshot_28_thumb.jpg": {
	  "source": "derivative",
	  "format": "JPEG Thumb",
	  "original": "screenshot_28.jpg",
	  "mtime": "1475584532",
	  "size": "4884",
	  "md5": "22c37b3909706a54304998fc576a739c",
	  "crc32": "826d2764",
	  "sha1": "80e47611f07938ed363deea3ac32b5611c553500"
	},
	"\/screenshot_29.jpg": {
	  "source": "original",
	  "mtime": "1475584399",
	  "size": "296859",
	  "md5": "6c1cd4a3e4d390b5de67ae938517d096",
	  "crc32": "478b15e5",
	  "sha1": "d6bb88116d5c25763579cc085dd163d01e31ebe3",
	  "format": "JPEG",
	  "rotation": "0"
	},
	"\/screenshot_29_thumb.jpg": {
	  "source": "derivative",
	  "format": "JPEG Thumb",
	  "original": "screenshot_29.jpg",
	  "mtime": "1475584534",
	  "size": "4887",
	  "md5": "7c684c5e86d6fa9076c016c7c2149c2d",
	  "crc32": "a8fa7104",
	  "sha1": "aaa6ac52eaa8561a740c6e9ec582b9c6efcff131"
	},
	"\/screenshot_30.jpg": {
	  "source": "original",
	  "mtime": "1475584401",
	  "size": "296935",
	  "md5": "2cae65b5c64b87d6f43918cfa11deb51",
	  "crc32": "8a565fe1",
	  "sha1": "27d5de054db1caba87e4ad0f1e35a51ee1d8ae28",
	  "format": "JPEG",
	  "rotation": "0"
	},
	"\/screenshot_30_thumb.jpg": {
	  "source": "derivative",
	  "format": "JPEG Thumb",
	  "original": "screenshot_30.jpg",
	  "mtime": "1475584535",
	  "size": "4887",
	  "md5": "a1454984ebf976885ed6302bf11b6886",
	  "crc32": "8ac0e1bc",
	  "sha1": "4b6282935550a4ec2519fa895ca2049743fb17b3"
	},
	"\/screenshot_31.jpg": {
	  "source": "original",
	  "mtime": "1475584403",
	  "size": "296880",
	  "md5": "621c5f79c507c704ec0c81ee1d9e7ce4",
	  "crc32": "953b3aab",
	  "sha1": "70d4787206b0368f10d264dee9609b695994f622",
	  "format": "JPEG",
	  "rotation": "0"
	},
	"\/screenshot_31_thumb.jpg": {
	  "source": "derivative",
	  "format": "JPEG Thumb",
	  "original": "screenshot_31.jpg",
	  "mtime": "1475584537",
	  "size": "4887",
	  "md5": "b39507be92c1314b117eaa2a97e3b47c",
	  "crc32": "d648a353",
	  "sha1": "4a5e1d3a881e9c243264460c98589c37ac93d3c5"
	},
	"\/screenshot_32.jpg": {
	  "source": "original",
	  "mtime": "1475584408",
	  "size": "296907",
	  "md5": "fd34cf848d52c2334023e302cbc2c09c",
	  "crc32": "7cc593ef",
	  "sha1": "7e87bf90cf83d6286856b8dbf1d104049dd4fabb",
	  "format": "JPEG",
	  "rotation": "0"
	},
	"\/screenshot_32_thumb.jpg": {
	  "source": "derivative",
	  "format": "JPEG Thumb",
	  "original": "screenshot_32.jpg",
	  "mtime": "1475584538",
	  "size": "4888",
	  "md5": "f22ed99b77f02b4ae2236b2280a9295f",
	  "crc32": "ccb62b5b",
	  "sha1": "fcf5d49147b9a96a8a513e56f6540abb97d3a48c"
	},
	"\/screenshot_33.jpg": {
	  "source": "original",
	  "mtime": "1475584411",
	  "size": "296941",
	  "md5": "555303413f88f7ef3f0944ff16498ad8",
	  "crc32": "adddf087",
	  "sha1": "216fa1dc639681978f5e82ff5c8c4ccda27deba4",
	  "format": "JPEG",
	  "rotation": "0"
	},
	"\/screenshot_33_thumb.jpg": {
	  "source": "derivative",
	  "format": "JPEG Thumb",
	  "original": "screenshot_33.jpg",
	  "mtime": "1475584539",
	  "size": "4887",
	  "md5": "2315ec57a05ac5d0eaf0ed1ff867c4ef",
	  "crc32": "81d4140a",
	  "sha1": "813097519086276f7ceaae03b52fc2242edd85cb"
	},
	"\/screenshot_34.jpg": {
	  "source": "original",
	  "mtime": "1475584413",
	  "size": "297205",
	  "md5": "33ef9f39b2d7b5ad2c0c734872095945",
	  "crc32": "b2ed40d8",
	  "sha1": "29253af11f7c234f08389a779c50bf257c05d334",
	  "format": "JPEG",
	  "rotation": "0"
	},
	"\/screenshot_34_thumb.jpg": {
	  "source": "derivative",
	  "format": "JPEG Thumb",
	  "original": "screenshot_34.jpg",
	  "mtime": "1475584541",
	  "size": "4890",
	  "md5": "c8652fecbc000f05725cc2d0ab849175",
	  "crc32": "fb3035f9",
	  "sha1": "f0ed6dad72185cf24b78825e833b56e85e0b8193"
	},
	"\/screenshot_35.jpg": {
	  "source": "original",
	  "mtime": "1475584415",
	  "size": "296369",
	  "md5": "5bd05f333a994fb023298fec7f094d9e",
	  "crc32": "ee6a15e3",
	  "sha1": "5da176f24401f9ca1c0dbcbc0a14360d85c8b671",
	  "format": "JPEG",
	  "rotation": "0"
	},
	"\/screenshot_35_thumb.jpg": {
	  "source": "derivative",
	  "format": "JPEG Thumb",
	  "original": "screenshot_35.jpg",
	  "mtime": "1475584527",
	  "size": "4881",
	  "md5": "1c52241d6bbd2fa9c4ba8a865e9bb944",
	  "crc32": "7b3af549",
	  "sha1": "17d214b4285142e7ae9c2d309967ca4aafb950e6"
	},
	"\/screenshot_36.jpg": {
	  "source": "original",
	  "mtime": "1475584417",
	  "size": "296028",
	  "md5": "7063838cb3a8f06351aaa85f0f2ca17a",
	  "crc32": "6fc2a89b",
	  "sha1": "9f74b2b8862f0b6ecb3fc62df0bc9de751cd2daf",
	  "format": "JPEG",
	  "rotation": "0"
	},
	"\/screenshot_36_thumb.jpg": {
	  "source": "derivative",
	  "format": "JPEG Thumb",
	  "original": "screenshot_36.jpg",
	  "mtime": "1475584528",
	  "size": "4881",
	  "md5": "a0f27cbd95c8ca4371b147162cd72a45",
	  "crc32": "e04a6752",
	  "sha1": "01a34c8a2b7a62e0d9370e70f2e2df857a1ff7cf"
	},
	"\/screenshot_37.jpg": {
	  "source": "original",
	  "mtime": "1475584419",
	  "size": "296028",
	  "md5": "6f7f7f93afc354e13f4cf3c7ab4b92d6",
	  "crc32": "ba6d3ed4",
	  "sha1": "e2376d5ebb7502507bf498e3a1c84d0617b30554",
	  "format": "JPEG",
	  "rotation": "0"
	},
	"\/screenshot_37_thumb.jpg": {
	  "source": "derivative",
	  "format": "JPEG Thumb",
	  "original": "screenshot_37.jpg",
	  "mtime": "1475584546",
	  "size": "4873",
	  "md5": "7921324c85fb64972051a13197716c48",
	  "crc32": "31188aa0",
	  "sha1": "6407d57fa75eb861cc05a9160334ed7569e67ae5"
	},
	"\/screenshot_38.jpg": {
	  "source": "original",
	  "mtime": "1475584422",
	  "size": "300367",
	  "md5": "9d1167c18388fd69bb1ada062b56cf45",
	  "crc32": "b2e8ee98",
	  "sha1": "c51ec7a4e397e82a7186928d518c608e57ca0a6b",
	  "format": "JPEG",
	  "rotation": "0"
	},
	"\/screenshot_38_thumb.jpg": {
	  "source": "derivative",
	  "format": "JPEG Thumb",
	  "original": "screenshot_38.jpg",
	  "mtime": "1475584547",
	  "size": "4941",
	  "md5": "7c6680ecc1ac8afc51096cfe87f6496f",
	  "crc32": "0e28cc5d",
	  "sha1": "63462728c26b36cdffb825f9ec3f4903fac9630c"
	},
	"\/screenshot_39.jpg": {
	  "source": "original",
	  "mtime": "1475584424",
	  "size": "300287",
	  "md5": "f90db3f818651de3e4b0b6ac3bfe0c0f",
	  "crc32": "53d25f08",
	  "sha1": "f44517f5fe512121c044c6773838762f1d663713",
	  "format": "JPEG",
	  "rotation": "0"
	},
	"\/screenshot_39_thumb.jpg": {
	  "source": "derivative",
	  "format": "JPEG Thumb",
	  "original": "screenshot_39.jpg",
	  "mtime": "1475584549",
	  "size": "4935",
	  "md5": "bc468ea882d59a7ac0da49564f25b5a2",
	  "crc32": "2e43d763",
	  "sha1": "5b7122df91d043802605fb9d746a74487950183d"
	},
	"\/screenshot_40.jpg": {
	  "source": "original",
	  "mtime": "1475584427",
	  "size": "282730",
	  "md5": "c415ddffddb2e98cc21ff0bdd6a234bf",
	  "crc32": "9431f734",
	  "sha1": "05f6f2d778052725d35724331baba1bb0667bb26",
	  "format": "JPEG",
	  "rotation": "0"
	},
	"\/screenshot_40_thumb.jpg": {
	  "source": "derivative",
	  "format": "JPEG Thumb",
	  "original": "screenshot_40.jpg",
	  "mtime": "1475584551",
	  "size": "4240",
	  "md5": "25afd19ca90925d1759c6de084e4dee9",
	  "crc32": "a82215e9",
	  "sha1": "1a798e89bdb87bb01ad8feeb20728451c706b8b9"
	},
	"\/screenshot_41.jpg": {
	  "source": "original",
	  "mtime": "1475584430",
	  "size": "249926",
	  "md5": "e65f200f5a9a4eb23e4032769008e297",
	  "crc32": "63179faf",
	  "sha1": "8b1f09691409f2fc7dcf404a40cc3bc41785a64d",
	  "format": "JPEG",
	  "rotation": "0"
	},
	"\/screenshot_41_thumb.jpg": {
	  "source": "derivative",
	  "format": "JPEG Thumb",
	  "original": "screenshot_41.jpg",
	  "mtime": "1475584553",
	  "size": "3599",
	  "md5": "a67bd5356e587c7dace56fd0ff183f86",
	  "crc32": "ebb72142",
	  "sha1": "b136470273457b1546737b1432ebb734143dd6dd"
	},
	"\/screenshot_42.jpg": {
	  "source": "original",
	  "mtime": "1475584432",
	  "size": "293580",
	  "md5": "2e121a3e3280437817fb47c8053838a4",
	  "crc32": "f33c0275",
	  "sha1": "5aeac14d55d2d05ece6d75d3369cf55d2dd555b4",
	  "format": "JPEG",
	  "rotation": "0"
	},
	"\/screenshot_42_thumb.jpg": {
	  "source": "derivative",
	  "format": "JPEG Thumb",
	  "original": "screenshot_42.jpg",
	  "mtime": "1475584555",
	  "size": "4592",
	  "md5": "f537c1b94828e2d391b9601a8802c6d8",
	  "crc32": "4b04427c",
	  "sha1": "ec5592695d58f7b234914fbac6fa9e6ee5fedbdf"
	},
	"\/screenshot_43.jpg": {
	  "source": "original",
	  "mtime": "1475584434",
	  "size": "292808",
	  "md5": "3d888ebd87436fb259d197b50cb75f45",
	  "crc32": "7861920d",
	  "sha1": "3fb61ac50ce9c6a78c5296ca7b7f937e4b928155",
	  "format": "JPEG",
	  "rotation": "0"
	},
	"\/screenshot_43_thumb.jpg": {
	  "source": "derivative",
	  "format": "JPEG Thumb",
	  "original": "screenshot_43.jpg",
	  "mtime": "1475584556",
	  "size": "4578",
	  "md5": "87e6fe73680b44b7c5319d1cb304244a",
	  "crc32": "d693251e",
	  "sha1": "c3212708d466de1b8ed7034d28d4f9d77e939894"
	},
	"\/screenshot_44.jpg": {
	  "source": "original",
	  "mtime": "1475584436",
	  "size": "292953",
	  "md5": "7536ca182a03af9da44c6e0ab422f88b",
	  "crc32": "fcd8a7c9",
	  "sha1": "c5bf0b894c82e32e5a02e4c0f5b8cb950560306e",
	  "format": "JPEG",
	  "rotation": "0"
	},
	"\/screenshot_44_thumb.jpg": {
	  "source": "derivative",
	  "format": "JPEG Thumb",
	  "original": "screenshot_44.jpg",
	  "mtime": "1475584557",
	  "size": "4580",
	  "md5": "8ebeae671ae4b9d161dd60828a4b3b52",
	  "crc32": "fb0420e3",
	  "sha1": "a69a2dbce6aa4afc9ebf75cd341a5883829263a0"
	},
	"\/screenshot_45.jpg": {
	  "source": "original",
	  "mtime": "1475584439",
	  "size": "292945",
	  "md5": "f83f7d18ec8b87e6cddaf37f86ecf523",
	  "crc32": "6b591443",
	  "sha1": "9247857176a435f98c501f9b54af5b9450c87548",
	  "format": "JPEG",
	  "rotation": "0"
	},
	"\/screenshot_45_thumb.jpg": {
	  "source": "derivative",
	  "format": "JPEG Thumb",
	  "original": "screenshot_45.jpg",
	  "mtime": "1475584559",
	  "size": "4580",
	  "md5": "af97ef091db4cde87a4d4516a1a1e9cf",
	  "crc32": "6755d3b1",
	  "sha1": "c9041c9311f97799ac2d9cfe0d877451ae949932"
	},
	"\/screenshot_46.jpg": {
	  "source": "original",
	  "mtime": "1475584441",
	  "size": "292941",
	  "md5": "76e116945ce35f83a60b1ff6f6408b90",
	  "crc32": "ae5d6a4e",
	  "sha1": "2229e625ddc369248b1d56c957e67f5188700231",
	  "format": "JPEG",
	  "rotation": "0"
	},
	"\/screenshot_46_thumb.jpg": {
	  "source": "derivative",
	  "format": "JPEG Thumb",
	  "original": "screenshot_46.jpg",
	  "mtime": "1475584561",
	  "size": "4580",
	  "md5": "080e6706619f6c87a701fbdeeb4e7b24",
	  "crc32": "040519f9",
	  "sha1": "b716d78db9fa9ccab417006382a10359016b01e4"
	},
	"\/screenshot_47.jpg": {
	  "source": "original",
	  "mtime": "1475584449",
	  "size": "292936",
	  "md5": "9fc330402faa62e2a9359fef0472e64b",
	  "crc32": "5427ef23",
	  "sha1": "dd3415d3a116831a8afcdcb4474b4180d05fd21e",
	  "format": "JPEG",
	  "rotation": "0"
	},
	"\/screenshot_47_thumb.jpg": {
	  "source": "derivative",
	  "format": "JPEG Thumb",
	  "original": "screenshot_47.jpg",
	  "mtime": "1475584562",
	  "size": "4580",
	  "md5": "586910b775fc9244cb7f6fce6ddf1952",
	  "crc32": "26d25587",
	  "sha1": "3382d1fd5239e779c26ac20efe826e97036493cb"
	},
	"\/uw_demo.zip": {
	  "source": "original",
	  "format": "ZIP",
	  "mtime": "1471041526",
	  "size": "2333342",
	  "md5": "c9453cf3c473778642455ec9585f6a82",
	  "crc32": "9334f0ff",
	  "sha1": "3a2c599637694ffc71d99c203daa9f1f42338121"
	},
	"\/uw_demo_screenshot.gif": {
	  "source": "original",
	  "mtime": "1475584476",
	  "size": "4980143",
	  "md5": "839c55b7eae9a048ee44537d0fa13027",
	  "crc32": "d8bdb41e",
	  "sha1": "15887a7eec5c461fbde1fc7fdcc76ba5b07d7ee4",
	  "format": "Emulator Screenshot"
	}
  },
  "misc": {
	"image": "https:\/\/ia600302.us.archive.org\/9\/items\/UltimaUnderworldTheStygianAbyssDemo\/UltimaUnderworldTheStygianAbyssDemo.gif",
	"collection-title": "Classic PC Games"
  },
  "item": {
	"downloads": 1002,
	"week": 10,
	"month": 18
  }
}